Metadata-Version: 2.1
Name: lex2
Version: 1.1.1
Summary: Flexible, ruleset-based tokenizer using regex.
Home-page: UNKNOWN
Author: DeltaRazero
Author-email: deltarazero@gmail.com
License: zlib
Keywords: lexer tokenizer sphinx
Platform: UNKNOWN
Classifier: Programming Language :: Python :: 3
Classifier: Programming Language :: Python :: 3 :: Only
Classifier: Operating System :: OS Independent
Classifier: License :: OSI Approved :: zlib/libpng License
Classifier: Development Status :: 5 - Production/Stable
Classifier: Intended Audience :: Developers
Classifier: Topic :: Scientific/Engineering :: Information Analysis
Classifier: Topic :: Software Development :: Compilers
Classifier: Topic :: Text Processing
Requires-Python: >=3.6
